gemmaapi/__init__.py
gemmaapi/gemmaapi.py
gemmaapi-0.1.36.dist-info/LICENSE
gemmaapi-0.1.36.dist-info/METADATA
gemmaapi-0.1.36.dist-info/WHEEL
gemmaapi-0.1.36.dist-info/RECORD
