Metadata-Version: 2.1
Name: gemmaapi
Version: 0.1.36
Summary: Gemma API python SDK
License: MIT
Author: Ed Reis
Author-email: ed@llama-api.com
Requires-Python: >=3.9,<4.0
Classifier: License :: OSI Approved :: MIT License
Classifier: Programming Language :: Python :: 3
Classifier: Programming Language :: Python :: 3.9
Classifier: Programming Language :: Python :: 3.10
Classifier: Programming Language :: Python :: 3.11
Requires-Dist: aiohttp (>=3.8.5,<4.0.0)
Requires-Dist: nest-asyncio (>=1.5.6,<2.0.0)
Requires-Dist: requests (>=2.27.1,<3.0.0)
